MANIFEST.in
hr_timesheet_data.xml
hr_timesheet_demo.xml
hr_timesheet_installer.xml
hr_timesheet_report.xml
hr_timesheet_view.xml
hr_timesheet_wizard.xml
setup.py
./__init__.py
./__openerp__.py
./hr_timesheet.py
./report/__init__.py
./report/user_timesheet.py
./report/users_timesheet.py
./wizard/__init__.py
./wizard/hr_timesheet_print_employee.py
./wizard/hr_timesheet_print_users.py
./wizard/hr_timesheet_sign_in_out.py
i18n/ar.po
i18n/bg.po
i18n/bs.po
i18n/ca.po
i18n/cs.po
i18n/da.po
i18n/de.po
i18n/el.po
i18n/en_GB.po
i18n/es.po
i18n/es_AR.po
i18n/es_CR.po
i18n/es_EC.po
i18n/es_MX.po
i18n/es_VE.po
i18n/et.po
i18n/fi.po
i18n/fr.po
i18n/gl.po
i18n/hr.po
i18n/hr_timesheet.pot
i18n/hu.po
i18n/id.po
i18n/it.po
i18n/ja.po
i18n/ko.po
i18n/lt.po
i18n/lv.po
i18n/mk.po
i18n/mn.po
i18n/nb.po
i18n/nl.po
i18n/nl_BE.po
i18n/pl.po
i18n/pt.po
i18n/pt_BR.po
i18n/ro.po
i18n/ru.po
i18n/sl.po
i18n/sq.po
i18n/sr@latin.po
i18n/sv.po
i18n/th.po
i18n/tlh.po
i18n/tr.po
i18n/uk.po
i18n/vi.po
i18n/zh_CN.po
i18n/zh_TW.po
images/hr_timesheet_lines.jpeg
openerp_hr_timesheet.egg-info/PKG-INFO
openerp_hr_timesheet.egg-info/SOURCES.txt
openerp_hr_timesheet.egg-info/dependency_links.txt
openerp_hr_timesheet.egg-info/requires.txt
openerp_hr_timesheet.egg-info/top_level.txt
process/hr_timesheet_process.xml
report/custom_default.xsl
report/custom_rml.xsl
report/user_timesheet.xsl
report/users_timesheet.xsl
security/hr_timesheet_security.xml
security/ir.model.access.csv
test/hr_timesheet_demo.yml
test/hr_timesheet_report.yml
test/test_hr_timesheet.yml
wizard/hr_timesheet_print_employee_view.xml
wizard/hr_timesheet_print_users_view.xml
wizard/hr_timesheet_sign_in_out_view.xml